pytileproj/__init__.py
pytileproj/base.py
pytileproj/geometry.py
pytileproj/utmgrid.py
pytileproj/data/__init__.py
pytileproj/data/utm/make_utm_shapefiles.py
pytileproj/data/utm/make_utmdata.py
pytileproj/data/utm/utmgrid.dat
pytileproj/data/utm/grids/000_grids_combined/UTM_UPS_V10_ALL_ZONES_GEOG_ZONE.dbf
pytileproj/data/utm/grids/000_grids_combined/UTM_UPS_V10_ALL_ZONES_GEOG_ZONE.prj
pytileproj/data/utm/grids/000_grids_combined/UTM_UPS_V10_ALL_ZONES_GEOG_ZONE.shp
pytileproj/data/utm/grids/000_grids_combined/UTM_UPS_V10_ALL_ZONES_GEOG_ZONE.shx
pytileproj/data/utm/grids/Z00A/GEOG/UTM_UPS_V10_Z00A_GEOG_ZONE.dbf
pytileproj/data/utm/grids/Z00A/GEOG/UTM_UPS_V10_Z00A_GEOG_ZONE.prj
pytileproj/data/utm/grids/Z00A/GEOG/UTM_UPS_V10_Z00A_GEOG_ZONE.shp
pytileproj/data/utm/grids/Z00A/GEOG/UTM_UPS_V10_Z00A_GEOG_ZONE.shx
pytileproj/data/utm/grids/Z00B/GEOG/UTM_UPS_V10_Z00B_GEOG_ZONE.dbf
pytileproj/data/utm/grids/Z00B/GEOG/UTM_UPS_V10_Z00B_GEOG_ZONE.prj
pytileproj/data/utm/grids/Z00B/GEOG/UTM_UPS_V10_Z00B_GEOG_ZONE.shp
pytileproj/data/utm/grids/Z00B/GEOG/UTM_UPS_V10_Z00B_GEOG_ZONE.shx
pytileproj/data/utm/grids/Z00Y/GEOG/UTM_UPS_V10_Z00Y_GEOG_ZONE.dbf
pytileproj/data/utm/grids/Z00Y/GEOG/UTM_UPS_V10_Z00Y_GEOG_ZONE.prj
pytileproj/data/utm/grids/Z00Y/GEOG/UTM_UPS_V10_Z00Y_GEOG_ZONE.shp
pytileproj/data/utm/grids/Z00Y/GEOG/UTM_UPS_V10_Z00Y_GEOG_ZONE.shx
pytileproj/data/utm/grids/Z00Z/GEOG/UTM_UPS_V10_Z00Z_GEOG_ZONE.dbf
pytileproj/data/utm/grids/Z00Z/GEOG/UTM_UPS_V10_Z00Z_GEOG_ZONE.prj
pytileproj/data/utm/grids/Z00Z/GEOG/UTM_UPS_V10_Z00Z_GEOG_ZONE.shp
pytileproj/data/utm/grids/Z00Z/GEOG/UTM_UPS_V10_Z00Z_GEOG_ZONE.shx
pytileproj/data/utm/grids/Z01N/GEOG/UTM_UPS_V10_Z01N_GEOG_ZONE.dbf
pytileproj/data/utm/grids/Z01N/GEOG/UTM_UPS_V10_Z01N_GEOG_ZONE.prj
pytileproj/data/utm/grids/Z01N/GEOG/UTM_UPS_V10_Z01N_GEOG_ZONE.shp
pytileproj/data/utm/grids/Z01N/GEOG/UTM_UPS_V10_Z01N_GEOG_ZONE.shx
pytileproj/data/utm/grids/Z01S/GEOG/UTM_UPS_V10_Z01S_GEOG_ZONE.dbf
pytileproj-0.1.0.dist-info/licenses/LICENSE.txt
pytileproj-0.1.0.dist-info/METADATA
pytileproj-0.1.0.dist-info/WHEEL
pytileproj-0.1.0.dist-info/top_level.txt
pytileproj-0.1.0.dist-info/RECORD
